CHANGELOG.rst
LICENSE
MANIFEST.in
README.rst
VERSION
requirements.txt
setup.cfg
setup.py
examples/__init__.py
examples/pass_by_reference.py
powerful_pipes/__init__.py
powerful_pipes/async_io_utils.py
powerful_pipes/exceptions.py
powerful_pipes/io_utils.py
powerful_pipes/json_schema.py
powerful_pipes/json_utils.py
powerful_pipes/logging.py
powerful_pipes/typing.py
powerful_pipes.egg-info/PKG-INFO
powerful_pipes.egg-info/SOURCES.txt
powerful_pipes.egg-info/dependency_links.txt
powerful_pipes.egg-info/entry_points.txt
powerful_pipes.egg-info/requires.txt
powerful_pipes.egg-info/top_level.txt
powerful_pipes.egg-info/zip-safe
powerful_pipes/bin/__init__.py
powerful_pipes/bin/ticker.py