Metadata-Version: 2.1
Name: powerful-pipes
Version: 1.1.3
Summary: Powerful pipes
Home-page: https://github.com/42Crunch/powerful-pipes
Author: 42Crunch team
Author-email: dev@42crunch.com
License: License :: OSI Approved :: Apache Software License
Platform: UNKNOWN
Classifier: License :: OSI Approved :: Apache Software License
Classifier: Programming Language :: Python :: 3.8
Classifier: Programming Language :: Python :: 3.9
Classifier: Programming Language :: Python :: 3.10
Classifier: Environment :: Console
Classifier: Operating System :: POSIX
Classifier: Operating System :: MacOS
Classifier: Operating System :: OS Independent
Classifier: Operating System :: Microsoft :: Windows
Classifier: Intended Audience :: Other Audience
Classifier: Intended Audience :: System Administrators
Provides-Extra: performance
